README.rst
setup.cfg
setup.py
gtxstorage/__init__.py
gtxstorage/api.py
gtxstorage/compat.py
gtxstorage/copy_conditions.py
gtxstorage/definitions.py
gtxstorage/error.py
gtxstorage/fold_case_dict.py
gtxstorage/helpers.py
gtxstorage/parsers.py
gtxstorage/policy.py
gtxstorage/post_policy.py
gtxstorage/signer.py
gtxstorage/thread_pool.py
gtxstorage/xml_marshal.py
gtxstorage.egg-info/PKG-INFO
gtxstorage.egg-info/SOURCES.txt
gtxstorage.egg-info/dependency_links.txt
gtxstorage.egg-info/requires.txt
gtxstorage.egg-info/top_level.txt