Metadata-Version: 1.1
Name: gtxstorage
Version: 1.1.0
Summary: GTXStorage Python Library for Amazon S3 Compatible Cloud Storage for Python
Home-page: https://github.com/Genetalks/gtxstorage-py
Author: GTXStorage, Inc.
Author-email: dev@gtxstorage.io
License: Apache License 2.0
Download-URL: https://github.com/Genetalks/gtxstorage-py
Platform: UNKNOWN
Classifier: Development Status :: 5 - Production/Stable
Classifier: Intended Audience :: Developers
Classifier: License :: OSI Approved :: Apache Software License
Classifier: Natural Language :: English
Classifier: Operating System :: OS Independent
Classifier: Programming Language :: Python
Classifier: Programming Language :: Python :: 2.7
Classifier: Programming Language :: Python :: 3.3
Classifier: Programming Language :: Python :: 3.4
Classifier: Programming Language :: Python :: 3.5
Classifier: Topic :: Software Development :: Libraries :: Python Modules
